[
  {
    "inputs": [],
    "stateMutability": "nonpayable",
    "type": "constructor"
  },
  {
    "anonymous": false,
    "inputs": [
      {
        "indexed": false,
        "internalType": "address",
        "name": "",
        "type": "address"
      },
      {
        "indexed": false,
        "internalType": "address",
        "name": "",
        "type": "address"
      },
      {
        "indexed": false,
        "internalType": "uint256",
        "name": "",
        "type": "uint256"
      },
      {
        "indexed": false,
        "internalType": "uint256",
        "name": "",
        "type": "uint256"
      },
      {
        "indexed": false,
        "internalType": "string",
        "name": "",
        "type": "string"
      }
    ],
    "name": "TestEvent",
    "type": "event"
  },
  {
    "stateMutability": "payable",
    "type": "fallback"
  },
  {
    "inputs": [
      {
        "internalType": "address",
        "name": "pool",
        "type": "address"
      },
      {
        "internalType": "address",
        "name": "input",
        "type": "address"
      },
      {
        "internalType": "address",
        "name": "output",
        "type": "address"
      },
      {
        "internalType": "uint256",
        "name": "amount",
        "type": "uint256"
      },
      {
        "internalType": "uint256",
        "name": "minimum",
        "type": "uint256"
      }
    ],
    "name": "swap",
    "outputs": [
      {
        "internalType": "uint256",
        "name": "",
        "type": "uint256"
      },
      {
        "internalType": "uint256",
        "name": "",
        "type": "uint256"
      }
    ],
    "stateMutability": "payable",
    "type": "function"
  }
]