[
  {
    "inputs": [],
    "stateMutability": "nonpayable",
    "type": "constructor"
  },
  {
    "anonymous": false,
    "inputs": [
      {
        "indexed": true,
        "internalType": "bytes32",
        "name": "id",
        "type": "bytes32"
      }
    ],
    "name": "ChainlinkCancelled",
    "type": "event"
  },
  {
    "anonymous": false,
    "inputs": [
      {
        "indexed": true,
        "internalType": "bytes32",
        "name": "id",
        "type": "bytes32"
      }
    ],
    "name": "ChainlinkFulfilled",
    "type": "event"
  },
  {
    "anonymous": false,
    "inputs": [
      {
        "indexed": true,
        "internalType": "bytes32",
        "name": "id",
        "type": "bytes32"
      }
    ],
    "name": "ChainlinkRequested",
    "type": "event"
  },
  {
    "anonymous": false,
    "inputs": [
      {
        "indexed": true,
        "internalType": "address",
        "name": "from",
        "type": "address"
      },
      {
        "indexed": true,
        "internalType": "address",
        "name": "to",
        "type": "address"
      }
    ],
    "name": "OwnershipTransferRequested",
    "type": "event"
  },
  {
    "anonymous": false,
    "inputs": [
      {
        "indexed": true,
        "internalType": "address",
        "name": "from",
        "type": "address"
      },
      {
        "indexed": true,
        "internalType": "address",
        "name": "to",
        "type": "address"
      }
    ],
    "name": "OwnershipTransferred",
    "type": "event"
  },
  {
    "anonymous": false,
    "inputs": [
      {
        "indexed": true,
        "internalType": "bytes32",
        "name": "requestId",
        "type": "bytes32"
      },
      {
        "indexed": false,
        "internalType": "uint256",
        "name": "soy",
        "type": "uint256"
      },
      {
        "indexed": false,
        "internalType": "uint256",
        "name": "wheat",
        "type": "uint256"
      },
      {
        "indexed": false,
        "internalType": "uint256",
        "name": "rice",
        "type": "uint256"
      },
      {
        "indexed": false,
        "internalType": "uint256",
        "name": "corn",
        "type": "uint256"
      }
    ],
    "name": "RequestFulfilledData",
    "type": "event"
  },
  {
    "inputs": [],
    "name": "acceptOwnership",
    "outputs": [],
    "stateMutability": "nonpayable",
    "type": "function"
  },
  {
    "inputs": [
      {
        "internalType": "bytes32",
        "name": "requestId",
        "type": "bytes32"
      },
      {
        "internalType": "uint256",
        "name": "_soy",
        "type": "uint256"
      },
      {
        "internalType": "uint256",
        "name": "_wheat",
        "type": "uint256"
      },
      {
        "internalType": "uint256",
        "name": "_rice",
        "type": "uint256"
      },
      {
        "internalType": "uint256",
        "name": "_corn",
        "type": "uint256"
      }
    ],
    "name": "fulfillData",
    "outputs": [],
    "stateMutability": "nonpayable",
    "type": "function"
  },
  {
    "inputs": [],
    "name": "oraclePrices",
    "outputs": [
      {
        "internalType": "contract OraclePrices",
        "name": "",
        "type": "address"
      }
    ],
    "stateMutability": "view",
    "type": "function"
  },
  {
    "inputs": [],
    "name": "owner",
    "outputs": [
      {
        "internalType": "address",
        "name": "",
        "type": "address"
      }
    ],
    "stateMutability": "view",
    "type": "function"
  },
  {
    "inputs": [],
    "name": "requestData",
    "outputs": [],
    "stateMutability": "nonpayable",
    "type": "function"
  },
  {
    "inputs": [
      {
        "internalType": "address",
        "name": "to",
        "type": "address"
      }
    ],
    "name": "transferOwnership",
    "outputs": [],
    "stateMutability": "nonpayable",
    "type": "function"
  }
]