[
  {
    "inputs": [
      {
        "internalType": "address",
        "name": "_locker",
        "type": "address"
      }
    ],
    "stateMutability": "nonpayable",
    "type": "constructor"
  },
  {
    "inputs": [],
    "name": "LOCKER",
    "outputs": [
      {
        "internalType": "contract ILocker",
        "name": "",
        "type": "address"
      }
    ],
    "stateMutability": "view",
    "type": "function"
  },
  {
    "inputs": [
      {
        "internalType": "address",
        "name": "_caller",
        "type": "address"
      }
    ],
    "name": "isAuthenticated",
    "outputs": [
      {
        "internalType": "bool",
        "name": "",
        "type": "bool"
      }
    ],
    "stateMutability": "view",
    "type": "function"
  },
  {
    "inputs": [
      {
        "internalType": "contract IERC20",
        "name": "token",
        "type": "address"
      },
      {
        "internalType": "address",
        "name": "spender",
        "type": "address"
      },
      {
        "internalType": "uint256",
        "name": "amount",
        "type": "uint256"
      }
    ],
    "name": "setTokenApproval",
    "outputs": [],
    "stateMutability": "nonpayable",
    "type": "function"
  },
  {
    "inputs": [
      {
        "internalType": "contract IERC20",
        "name": "token",
        "type": "address"
      },
      {
        "internalType": "address",
        "name": "receiver",
        "type": "address"
      },
      {
        "internalType": "uint256",
        "name": "amount",
        "type": "uint256"
      }
    ],
    "name": "transferToken",
    "outputs": [],
    "stateMutability": "nonpayable",
    "type": "function"
  },
  {
    "inputs": [],
    "name": "withdrawFromLock",
    "outputs": [],
    "stateMutability": "nonpayable",
    "type": "function"
  }
]